MANIFEST.in
README.rst
setup.py
django_resumable.egg-info/PKG-INFO
django_resumable.egg-info/SOURCES.txt
django_resumable.egg-info/dependency_links.txt
django_resumable.egg-info/not-zip-safe
django_resumable.egg-info/requires.txt
django_resumable.egg-info/top_level.txt
resumable/__init__.py
resumable/fields.py
resumable/files.py
resumable/models.py
resumable/views.py
resumable/widgets.py
resumable/static/resumable/js/django-resumable.js
resumable/static/resumable/js/init.js
resumable/static/resumable/js/resumable.js
resumable/templates/resumable/file_input.html
resumable/tests/__init__.py
resumable/tests/app.py
resumable/tests/settings.py
resumable/tests/tests.py