Metadata-Version: 1.1
Name: django-resumable
Version: 0.2.0
Summary: Django resumable uploads
Home-page: https://github.com/jeanphix/django-resumable
Author: jean-philippe serafin
Author-email: serafinjp@gmail.com
License: MIT licence
Platform: UNKNOWN
Classifier: Development Status :: 5 - Production/Stable
Classifier: Environment :: Web Environment
Classifier: Framework :: Django
Classifier: Intended Audience :: Developers
Classifier: License :: OSI Approved :: MIT License
Classifier: Natural Language :: English
Classifier: Programming Language :: Python
